mypckg1/__init__.py
mypckg1/app.py
mypckg1-0.0.1.dist-info/METADATA
mypckg1-0.0.1.dist-info/WHEEL
mypckg1-0.0.1.dist-info/top_level.txt
mypckg1-0.0.1.dist-info/RECORD
