Metadata-Version: 2.1
Name: mypckg1
Version: 0.0.1
Summary: A useful module
Home-page: UNKNOWN
Author: Mb
Author-email: mad@ab.work
License: UNKNOWN
Platform: UNKNOWN
